LICENSE
MANIFEST.in
README.md
setup.py
py_sled.egg-info/PKG-INFO
py_sled.egg-info/SOURCES.txt
py_sled.egg-info/dependency_links.txt
py_sled.egg-info/requires.txt
py_sled.egg-info/top_level.txt
sled/__init__.py
sled/configuration_sled.py
sled/modeling_sled.py
sled/tokenization_sled.py
sled/tokenization_sled_fast.py