Metadata-Version: 2.1
Name: py-sled
Version: 0.1.0
Summary: SLED models use pretrained, short-range encoder-decoder models, and apply them over long-text inputs by splitting the input into multiple overlapping chunks, encoding each independently and perform fusion-in-decoder
Home-page: https://github.com/Mivg/SLED
Author: Maor Ivgi
Author-email: maor.ivgi@cs.tau.ac.il
License: UNKNOWN
Platform: UNKNOWN
Classifier: Intended Audience :: Developers
Classifier: Programming Language :: Python
Classifier: Programming Language :: Python :: 3
Classifier: License :: OSI Approved :: MIT License
Classifier: Natural Language :: English
Classifier: Topic :: Scientific/Engineering :: Artificial Intelligence
Classifier: Topic :: Text Processing
Requires-Python: >=3.7.0
Provides-Extra: t5
Provides-Extra: examples
Provides-Extra: dev
License-File: LICENSE
